{"config":{"output_file":null,"full_docs":false,"pub_only":true,"reachable_only":true,"distro_crate":false,"signatures":false,"borrow_data":false},"version":"0.19.1","compilation":{"directory":"/Users/yoiwasaki/.cargo/registry/src/github.com-1ecc6299db9ec823/rand_hc-0.2.0","program":"/Users/yoiwasaki/.rustup/toolchains/nightly-aarch64-apple-darwin/bin/rls","arguments":["--crate-name","rand_hc","--edition=2018","/Users/yoiwasaki/.cargo/registry/src/github.com-1ecc6299db9ec823/rand_hc-0.2.0/src/lib.rs","--json=diagnostic-rendered-ansi,artifacts,future-incompat","--crate-type","lib","--emit=dep-info,metadata","-C","embed-bitcode=no","-C","split-debuginfo=unpacked","-C","debuginfo=2","-C","metadata=8aba3d8b457aa3cf","-C","extra-filename=-8aba3d8b457aa3cf","--out-dir","/Users/yoiwasaki/rust/RustCoder/abc086/target/rls/debug/deps","-L","dependency=/Users/yoiwasaki/rust/RustCoder/abc086/target/rls/debug/deps","--extern","rand_core=/Users/yoiwasaki/rust/RustCoder/abc086/target/rls/debug/deps/librand_core-db6d5500e85600ae.rmeta","--cap-lints","allow","--error-format=json","--sysroot","/Users/yoiwasaki/.rustup/toolchains/nightly-aarch64-apple-darwin"],"output":"/Users/yoiwasaki/rust/RustCoder/abc086/target/rls/debug/deps/librand_hc-8aba3d8b457aa3cf.rmeta"},"prelude":{"crate_id":{"name":"rand_hc","disambiguator":[17847038505791913650,0]},"crate_root":"/Users/yoiwasaki/.cargo/registry/src/github.com-1ecc6299db9ec823/rand_hc-0.2.0/src","external_crates":[{"file_name":"/Users/yoiwasaki/.cargo/registry/src/github.com-1ecc6299db9ec823/rand_hc-0.2.0/src/lib.rs","num":1,"id":{"name":"core","disambiguator":[10692437436498197317,0]}},{"file_name":"/Users/yoiwasaki/.cargo/registry/src/github.com-1ecc6299db9ec823/rand_hc-0.2.0/src/lib.rs","num":2,"id":{"name":"compiler_builtins","disambiguator":[15047062486214017159,0]}},{"file_name":"/Users/yoiwasaki/.cargo/registry/src/github.com-1ecc6299db9ec823/rand_hc-0.2.0/src/lib.rs","num":3,"id":{"name":"rustc_std_workspace_core","disambiguator":[5564256416572278449,0]}},{"file_name":"/Users/yoiwasaki/.cargo/registry/src/github.com-1ecc6299db9ec823/rand_hc-0.2.0/src/hc128.rs","num":4,"id":{"name":"rand_core","disambiguator":[538111721718928933,0]}},{"file_name":"/Users/yoiwasaki/.cargo/registry/src/github.com-1ecc6299db9ec823/rand_hc-0.2.0/src/hc128.rs","num":5,"id":{"name":"std","disambiguator":[5192840566299105877,0]}},{"file_name":"/Users/yoiwasaki/.cargo/registry/src/github.com-1ecc6299db9ec823/rand_hc-0.2.0/src/hc128.rs","num":6,"id":{"name":"alloc","disambiguator":[59301030798865431,0]}},{"file_name":"/Users/yoiwasaki/.cargo/registry/src/github.com-1ecc6299db9ec823/rand_hc-0.2.0/src/hc128.rs","num":7,"id":{"name":"libc","disambiguator":[2278862341237512312,0]}},{"file_name":"/Users/yoiwasaki/.cargo/registry/src/github.com-1ecc6299db9ec823/rand_hc-0.2.0/src/hc128.rs","num":8,"id":{"name":"unwind","disambiguator":[6663670134978427585,0]}},{"file_name":"/Users/yoiwasaki/.cargo/registry/src/github.com-1ecc6299db9ec823/rand_hc-0.2.0/src/hc128.rs","num":9,"id":{"name":"cfg_if","disambiguator":[7123182725298081389,0]}},{"file_name":"/Users/yoiwasaki/.cargo/registry/src/github.com-1ecc6299db9ec823/rand_hc-0.2.0/src/hc128.rs","num":10,"id":{"name":"miniz_oxide","disambiguator":[17198901923018651019,0]}},{"file_name":"/Users/yoiwasaki/.cargo/registry/src/github.com-1ecc6299db9ec823/rand_hc-0.2.0/src/hc128.rs","num":11,"id":{"name":"rustc_std_workspace_alloc","disambiguator":[16083725143527070061,0]}},{"file_name":"/Users/yoiwasaki/.cargo/registry/src/github.com-1ecc6299db9ec823/rand_hc-0.2.0/src/hc128.rs","num":12,"id":{"name":"adler","disambiguator":[13046909016501762842,0]}},{"file_name":"/Users/yoiwasaki/.cargo/registry/src/github.com-1ecc6299db9ec823/rand_hc-0.2.0/src/hc128.rs","num":13,"id":{"name":"hashbrown","disambiguator":[16649028690006102982,0]}},{"file_name":"/Users/yoiwasaki/.cargo/registry/src/github.com-1ecc6299db9ec823/rand_hc-0.2.0/src/hc128.rs","num":14,"id":{"name":"std_detect","disambiguator":[828260593055482284,0]}},{"file_name":"/Users/yoiwasaki/.cargo/registry/src/github.com-1ecc6299db9ec823/rand_hc-0.2.0/src/hc128.rs","num":15,"id":{"name":"rustc_demangle","disambiguator":[10889954745355263166,0]}},{"file_name":"/Users/yoiwasaki/.cargo/registry/src/github.com-1ecc6299db9ec823/rand_hc-0.2.0/src/hc128.rs","num":16,"id":{"name":"addr2line","disambiguator":[9922028560906459012,0]}},{"file_name":"/Users/yoiwasaki/.cargo/registry/src/github.com-1ecc6299db9ec823/rand_hc-0.2.0/src/hc128.rs","num":17,"id":{"name":"gimli","disambiguator":[1864721895869041743,0]}},{"file_name":"/Users/yoiwasaki/.cargo/registry/src/github.com-1ecc6299db9ec823/rand_hc-0.2.0/src/hc128.rs","num":18,"id":{"name":"object","disambiguator":[16181643177631912245,0]}},{"file_name":"/Users/yoiwasaki/.cargo/registry/src/github.com-1ecc6299db9ec823/rand_hc-0.2.0/src/hc128.rs","num":19,"id":{"name":"memchr","disambiguator":[6834497564904288257,0]}},{"file_name":"/Users/yoiwasaki/.cargo/registry/src/github.com-1ecc6299db9ec823/rand_hc-0.2.0/src/hc128.rs","num":20,"id":{"name":"panic_unwind","disambiguator":[17427002673244215832,0]}},{"file_name":"/Users/yoiwasaki/.cargo/registry/src/github.com-1ecc6299db9ec823/rand_hc-0.2.0/src/hc128.rs","num":21,"id":{"name":"getrandom","disambiguator":[15969048941222539263,0]}},{"file_name":"/Users/yoiwasaki/.cargo/registry/src/github.com-1ecc6299db9ec823/rand_hc-0.2.0/src/hc128.rs","num":22,"id":{"name":"cfg_if","disambiguator":[6844393015850019137,0]}},{"file_name":"/Users/yoiwasaki/.cargo/registry/src/github.com-1ecc6299db9ec823/rand_hc-0.2.0/src/hc128.rs","num":23,"id":{"name":"libc","disambiguator":[2421152055605079957,0]}}],"span":{"file_name":"/Users/yoiwasaki/.cargo/registry/src/github.com-1ecc6299db9ec823/rand_hc-0.2.0/src/lib.rs","byte_start":356,"byte_end":797,"line_start":9,"line_end":23,"column_start":1,"column_end":38}},"imports":[{"kind":"Use","ref_id":{"krate":0,"index":72},"span":{"file_name":"/Users/yoiwasaki/.cargo/registry/src/github.com-1ecc6299db9ec823/rand_hc-0.2.0/src/lib.rs","byte_start":776,"byte_end":784,"line_start":23,"line_end":23,"column_start":17,"column_end":25},"alias_span":null,"name":"Hc128Rng","value":"","parent":{"krate":0,"index":0}},{"kind":"Use","ref_id":{"krate":0,"index":79},"span":{"file_name":"/Users/yoiwasaki/.cargo/registry/src/github.com-1ecc6299db9ec823/rand_hc-0.2.0/src/lib.rs","byte_start":786,"byte_end":795,"line_start":23,"line_end":23,"column_start":27,"column_end":36},"alias_span":null,"name":"Hc128Core","value":"","parent":{"krate":0,"index":0}}],"defs":[{"kind":"Mod","id":{"krate":0,"index":0},"span":{"file_name":"/Users/yoiwasaki/.cargo/registry/src/github.com-1ecc6299db9ec823/rand_hc-0.2.0/src/lib.rs","byte_start":356,"byte_end":797,"line_start":9,"line_end":23,"column_start":1,"column_end":38},"name":"","qualname":"::","value":"/Users/yoiwasaki/.cargo/registry/src/github.com-1ecc6299db9ec823/rand_hc-0.2.0/src/lib.rs","parent":null,"children":[{"krate":0,"index":1},{"krate":0,"index":2},{"krate":0,"index":3},{"krate":0,"index":4},{"krate":0,"index":65},{"krate":0,"index":66},{"krate":0,"index":69}],"decl_id":null,"docs":" The HC128 random number generator.\n","sig":null,"attributes":[{"value":"/ The HC128 random number generator.","span":{"file_name":"/Users/yoiwasaki/.cargo/registry/src/github.com-1ecc6299db9ec823/rand_hc-0.2.0/src/lib.rs","byte_start":356,"byte_end":394,"line_start":9,"line_end":9,"column_start":1,"column_end":39}},{"value":"deny(missing_docs)","span":{"file_name":"/Users/yoiwasaki/.cargo/registry/src/github.com-1ecc6299db9ec823/rand_hc-0.2.0/src/lib.rs","byte_start":611,"byte_end":633,"line_start":15,"line_end":15,"column_start":1,"column_end":23}},{"value":"deny(missing_debug_implementations)","span":{"file_name":"/Users/yoiwasaki/.cargo/registry/src/github.com-1ecc6299db9ec823/rand_hc-0.2.0/src/lib.rs","byte_start":634,"byte_end":673,"line_start":16,"line_end":16,"column_start":1,"column_end":40}},{"value":"no_std","span":{"file_name":"/Users/yoiwasaki/.cargo/registry/src/github.com-1ecc6299db9ec823/rand_hc-0.2.0/src/lib.rs","byte_start":736,"byte_end":746,"line_start":19,"line_end":19,"column_start":1,"column_end":11}}]},{"kind":"Struct","id":{"krate":0,"index":72},"span":{"file_name":"/Users/yoiwasaki/.cargo/registry/src/github.com-1ecc6299db9ec823/rand_hc-0.2.0/src/hc128.rs","byte_start":3862,"byte_end":3870,"line_start":67,"line_end":67,"column_start":12,"column_end":20},"name":"Hc128Rng","qualname":"::hc128::Hc128Rng","value":"","parent":null,"children":[],"decl_id":null,"docs":" A cryptographically secure random number generator that uses the HC-128\n algorithm.","sig":null,"attributes":[{"value":"/ A cryptographically secure random number generator that uses the HC-128","span":{"file_name":"/Users/yoiwasaki/.cargo/registry/src/github.com-1ecc6299db9ec823/rand_hc-0.2.0/src/hc128.rs","byte_start":1389,"byte_end":1464,"line_start":17,"line_end":17,"column_start":1,"column_end":76}},{"value":"/ algorithm.","span":{"file_name":"/Users/yoiwasaki/.cargo/registry/src/github.com-1ecc6299db9ec823/rand_hc-0.2.0/src/hc128.rs","byte_start":1465,"byte_end":1479,"line_start":18,"line_end":18,"column_start":1,"column_end":15}},{"value":"/","span":{"file_name":"/Users/yoiwasaki/.cargo/registry/src/github.com-1ecc6299db9ec823/rand_hc-0.2.0/src/hc128.rs","byte_start":1480,"byte_end":1483,"line_start":19,"line_end":19,"column_start":1,"column_end":4}},{"value":"/ HC-128 is a stream cipher designed by Hongjun Wu[^1], that we use as an","span":{"file_name":"/Users/yoiwasaki/.cargo/registry/src/github.com-1ecc6299db9ec823/rand_hc-0.2.0/src/hc128.rs","byte_start":1484,"byte_end":1559,"line_start":20,"line_end":20,"column_start":1,"column_end":76}},{"value":"/ RNG. It is selected as one of the \"stream ciphers suitable for widespread","span":{"file_name":"/Users/yoiwasaki/.cargo/registry/src/github.com-1ecc6299db9ec823/rand_hc-0.2.0/src/hc128.rs","byte_start":1560,"byte_end":1637,"line_start":21,"line_end":21,"column_start":1,"column_end":78}},{"value":"/ adoption\" by eSTREAM[^2].","span":{"file_name":"/Users/yoiwasaki/.cargo/registry/src/github.com-1ecc6299db9ec823/rand_hc-0.2.0/src/hc128.rs","byte_start":1638,"byte_end":1667,"line_start":22,"line_end":22,"column_start":1,"column_end":30}},{"value":"/","span":{"file_name":"/Users/yoiwasaki/.cargo/registry/src/github.com-1ecc6299db9ec823/rand_hc-0.2.0/src/hc128.rs","byte_start":1668,"byte_end":1671,"line_start":23,"line_end":23,"column_start":1,"column_end":4}},{"value":"/ HC-128 is an array based RNG. In this it is similar to RC-4 and ISAAC before","span":{"file_name":"/Users/yoiwasaki/.cargo/registry/src/github.com-1ecc6299db9ec823/rand_hc-0.2.0/src/hc128.rs","byte_start":1672,"byte_end":1752,"line_start":24,"line_end":24,"column_start":1,"column_end":81}},{"value":"/ it, but those have never been proven cryptographically secure (or have even","span":{"file_name":"/Users/yoiwasaki/.cargo/registry/src/github.com-1ecc6299db9ec823/rand_hc-0.2.0/src/hc128.rs","byte_start":1753,"byte_end":1832,"line_start":25,"line_end":25,"column_start":1,"column_end":80}},{"value":"/ been significantly compromised, as in the case of RC-4[^5]).","span":{"file_name":"/Users/yoiwasaki/.cargo/registry/src/github.com-1ecc6299db9ec823/rand_hc-0.2.0/src/hc128.rs","byte_start":1833,"byte_end":1897,"line_start":26,"line_end":26,"column_start":1,"column_end":65}},{"value":"/","span":{"file_name":"/Users/yoiwasaki/.cargo/registry/src/github.com-1ecc6299db9ec823/rand_hc-0.2.0/src/hc128.rs","byte_start":1898,"byte_end":1901,"line_start":27,"line_end":27,"column_start":1,"column_end":4}},{"value":"/ Because HC-128 works with simple indexing into a large array and with a few","span":{"file_name":"/Users/yoiwasaki/.cargo/registry/src/github.com-1ecc6299db9ec823/rand_hc-0.2.0/src/hc128.rs","byte_start":1902,"byte_end":1981,"line_start":28,"line_end":28,"column_start":1,"column_end":80}},{"value":"/ operations that parallelize well, it has very good performance. The size of","span":{"file_name":"/Users/yoiwasaki/.cargo/registry/src/github.com-1ecc6299db9ec823/rand_hc-0.2.0/src/hc128.rs","byte_start":1982,"byte_end":2061,"line_start":29,"line_end":29,"column_start":1,"column_end":80}},{"value":"/ the array it needs, 4kb, can however be a disadvantage.","span":{"file_name":"/Users/yoiwasaki/.cargo/registry/src/github.com-1ecc6299db9ec823/rand_hc-0.2.0/src/hc128.rs","byte_start":2062,"byte_end":2121,"line_start":30,"line_end":30,"column_start":1,"column_end":60}},{"value":"/","span":{"file_name":"/Users/yoiwasaki/.cargo/registry/src/github.com-1ecc6299db9ec823/rand_hc-0.2.0/src/hc128.rs","byte_start":2122,"byte_end":2125,"line_start":31,"line_end":31,"column_start":1,"column_end":4}},{"value":"/ This implementation is not based on the version of HC-128 submitted to the","span":{"file_name":"/Users/yoiwasaki/.cargo/registry/src/github.com-1ecc6299db9ec823/rand_hc-0.2.0/src/hc128.rs","byte_start":2126,"byte_end":2204,"line_start":32,"line_end":32,"column_start":1,"column_end":79}},{"value":"/ eSTREAM contest, but on a later version by the author with a few small","span":{"file_name":"/Users/yoiwasaki/.cargo/registry/src/github.com-1ecc6299db9ec823/rand_hc-0.2.0/src/hc128.rs","byte_start":2205,"byte_end":2279,"line_start":33,"line_end":33,"column_start":1,"column_end":75}},{"value":"/ improvements from December 15, 2009[^3].","span":{"file_name":"/Users/yoiwasaki/.cargo/registry/src/github.com-1ecc6299db9ec823/rand_hc-0.2.0/src/hc128.rs","byte_start":2280,"byte_end":2324,"line_start":34,"line_end":34,"column_start":1,"column_end":45}},{"value":"/","span":{"file_name":"/Users/yoiwasaki/.cargo/registry/src/github.com-1ecc6299db9ec823/rand_hc-0.2.0/src/hc128.rs","byte_start":2325,"byte_end":2328,"line_start":35,"line_end":35,"column_start":1,"column_end":4}},{"value":"/ HC-128 has no known weaknesses that are easier to exploit than doing a","span":{"file_name":"/Users/yoiwasaki/.cargo/registry/src/github.com-1ecc6299db9ec823/rand_hc-0.2.0/src/hc128.rs","byte_start":2329,"byte_end":2403,"line_start":36,"line_end":36,"column_start":1,"column_end":75}},{"value":"/ brute-force search of 2<sup>128</sup>. A very comprehensive analysis of the","span":{"file_name":"/Users/yoiwasaki/.cargo/registry/src/github.com-1ecc6299db9ec823/rand_hc-0.2.0/src/hc128.rs","byte_start":2404,"byte_end":2483,"line_start":37,"line_end":37,"column_start":1,"column_end":80}},{"value":"/ current state of known attacks / weaknesses of HC-128 is given in *Some","span":{"file_name":"/Users/yoiwasaki/.cargo/registry/src/github.com-1ecc6299db9ec823/rand_hc-0.2.0/src/hc128.rs","byte_start":2484,"byte_end":2559,"line_start":38,"line_end":38,"column_start":1,"column_end":76}},{"value":"/ Results On Analysis And Implementation Of HC-128 Stream Cipher*[^4].","span":{"file_name":"/Users/yoiwasaki/.cargo/registry/src/github.com-1ecc6299db9ec823/rand_hc-0.2.0/src/hc128.rs","byte_start":2560,"byte_end":2632,"line_start":39,"line_end":39,"column_start":1,"column_end":73}},{"value":"/","span":{"file_name":"/Users/yoiwasaki/.cargo/registry/src/github.com-1ecc6299db9ec823/rand_hc-0.2.0/src/hc128.rs","byte_start":2633,"byte_end":2636,"line_start":40,"line_end":40,"column_start":1,"column_end":4}},{"value":"/ The average cycle length is expected to be","span":{"file_name":"/Users/yoiwasaki/.cargo/registry/src/github.com-1ecc6299db9ec823/rand_hc-0.2.0/src/hc128.rs","byte_start":2637,"byte_end":2683,"line_start":41,"line_end":41,"column_start":1,"column_end":47}},{"value":"/ 2<sup>1024*32+10-1</sup> = 2<sup>32777</sup>.","span":{"file_name":"/Users/yoiwasaki/.cargo/registry/src/github.com-1ecc6299db9ec823/rand_hc-0.2.0/src/hc128.rs","byte_start":2684,"byte_end":2733,"line_start":42,"line_end":42,"column_start":1,"column_end":50}},{"value":"/ We support seeding with a 256-bit array, which matches the 128-bit key","span":{"file_name":"/Users/yoiwasaki/.cargo/registry/src/github.com-1ecc6299db9ec823/rand_hc-0.2.0/src/hc128.rs","byte_start":2734,"byte_end":2808,"line_start":43,"line_end":43,"column_start":1,"column_end":75}},{"value":"/ concatenated with a 128-bit IV from the stream cipher.","span":{"file_name":"/Users/yoiwasaki/.cargo/registry/src/github.com-1ecc6299db9ec823/rand_hc-0.2.0/src/hc128.rs","byte_start":2809,"byte_end":2867,"line_start":44,"line_end":44,"column_start":1,"column_end":59}},{"value":"/","span":{"file_name":"/Users/yoiwasaki/.cargo/registry/src/github.com-1ecc6299db9ec823/rand_hc-0.2.0/src/hc128.rs","byte_start":2868,"byte_end":2871,"line_start":45,"line_end":45,"column_start":1,"column_end":4}},{"value":"/ This implementation uses an output buffer of sixteen `u32` words, and uses","span":{"file_name":"/Users/yoiwasaki/.cargo/registry/src/github.com-1ecc6299db9ec823/rand_hc-0.2.0/src/hc128.rs","byte_start":2872,"byte_end":2950,"line_start":46,"line_end":46,"column_start":1,"column_end":79}},{"value":"/ [`BlockRng`] to implement the [`RngCore`] methods.","span":{"file_name":"/Users/yoiwasaki/.cargo/registry/src/github.com-1ecc6299db9ec823/rand_hc-0.2.0/src/hc128.rs","byte_start":2951,"byte_end":3005,"line_start":47,"line_end":47,"column_start":1,"column_end":55}},{"value":"/","span":{"file_name":"/Users/yoiwasaki/.cargo/registry/src/github.com-1ecc6299db9ec823/rand_hc-0.2.0/src/hc128.rs","byte_start":3006,"byte_end":3009,"line_start":48,"line_end":48,"column_start":1,"column_end":4}},{"value":"/ ## References","span":{"file_name":"/Users/yoiwasaki/.cargo/registry/src/github.com-1ecc6299db9ec823/rand_hc-0.2.0/src/hc128.rs","byte_start":3010,"byte_end":3027,"line_start":49,"line_end":49,"column_start":1,"column_end":18}},{"value":"/ [^1]: Hongjun Wu (2008). [\"The Stream Cipher HC-128\"](","span":{"file_name":"/Users/yoiwasaki/.cargo/registry/src/github.com-1ecc6299db9ec823/rand_hc-0.2.0/src/hc128.rs","byte_start":3028,"byte_end":3086,"line_start":50,"line_end":50,"column_start":1,"column_end":59}},{"value":"/       http://www.ecrypt.eu.org/stream/p3ciphers/hc/hc128_p3.pdf).","span":{"file_name":"/Users/yoiwasaki/.cargo/registry/src/github.com-1ecc6299db9ec823/rand_hc-0.2.0/src/hc128.rs","byte_start":3087,"byte_end":3156,"line_start":51,"line_end":51,"column_start":1,"column_end":70}},{"value":"/       *The eSTREAM Finalists*, LNCS 4986, pp. 39–47, Springer-Verlag.","span":{"file_name":"/Users/yoiwasaki/.cargo/registry/src/github.com-1ecc6299db9ec823/rand_hc-0.2.0/src/hc128.rs","byte_start":3157,"byte_end":3232,"line_start":52,"line_end":52,"column_start":1,"column_end":74}},{"value":"/","span":{"file_name":"/Users/yoiwasaki/.cargo/registry/src/github.com-1ecc6299db9ec823/rand_hc-0.2.0/src/hc128.rs","byte_start":3233,"byte_end":3236,"line_start":53,"line_end":53,"column_start":1,"column_end":4}},{"value":"/ [^2]: [eSTREAM: the ECRYPT Stream Cipher Project](","span":{"file_name":"/Users/yoiwasaki/.cargo/registry/src/github.com-1ecc6299db9ec823/rand_hc-0.2.0/src/hc128.rs","byte_start":3237,"byte_end":3291,"line_start":54,"line_end":54,"column_start":1,"column_end":55}},{"value":"/       http://www.ecrypt.eu.org/stream/)","span":{"file_name":"/Users/yoiwasaki/.cargo/registry/src/github.com-1ecc6299db9ec823/rand_hc-0.2.0/src/hc128.rs","byte_start":3292,"byte_end":3335,"line_start":55,"line_end":55,"column_start":1,"column_end":44}},{"value":"/","span":{"file_name":"/Users/yoiwasaki/.cargo/registry/src/github.com-1ecc6299db9ec823/rand_hc-0.2.0/src/hc128.rs","byte_start":3336,"byte_end":3339,"line_start":56,"line_end":56,"column_start":1,"column_end":4}},{"value":"/ [^3]: Hongjun Wu, [Stream Ciphers HC-128 and HC-256](","span":{"file_name":"/Users/yoiwasaki/.cargo/registry/src/github.com-1ecc6299db9ec823/rand_hc-0.2.0/src/hc128.rs","byte_start":3340,"byte_end":3397,"line_start":57,"line_end":57,"column_start":1,"column_end":58}},{"value":"/       https://www.ntu.edu.sg/home/wuhj/research/hc/index.html)","span":{"file_name":"/Users/yoiwasaki/.cargo/registry/src/github.com-1ecc6299db9ec823/rand_hc-0.2.0/src/hc128.rs","byte_start":3398,"byte_end":3464,"line_start":58,"line_end":58,"column_start":1,"column_end":67}},{"value":"/","span":{"file_name":"/Users/yoiwasaki/.cargo/registry/src/github.com-1ecc6299db9ec823/rand_hc-0.2.0/src/hc128.rs","byte_start":3465,"byte_end":3468,"line_start":59,"line_end":59,"column_start":1,"column_end":4}},{"value":"/ [^4]: Shashwat Raizada (January 2015),[\"Some Results On Analysis And","span":{"file_name":"/Users/yoiwasaki/.cargo/registry/src/github.com-1ecc6299db9ec823/rand_hc-0.2.0/src/hc128.rs","byte_start":3469,"byte_end":3541,"line_start":60,"line_end":60,"column_start":1,"column_end":73}},{"value":"/       Implementation Of HC-128 Stream Cipher\"](","span":{"file_name":"/Users/yoiwasaki/.cargo/registry/src/github.com-1ecc6299db9ec823/rand_hc-0.2.0/src/hc128.rs","byte_start":3542,"byte_end":3593,"line_start":61,"line_end":61,"column_start":1,"column_end":52}},{"value":"/       http://library.isical.ac.in:8080/jspui/bitstream/123456789/6636/1/TH431.pdf).","span":{"file_name":"/Users/yoiwasaki/.cargo/registry/src/github.com-1ecc6299db9ec823/rand_hc-0.2.0/src/hc128.rs","byte_start":3594,"byte_end":3681,"line_start":62,"line_end":62,"column_start":1,"column_end":88}},{"value":"/","span":{"file_name":"/Users/yoiwasaki/.cargo/registry/src/github.com-1ecc6299db9ec823/rand_hc-0.2.0/src/hc128.rs","byte_start":3682,"byte_end":3685,"line_start":63,"line_end":63,"column_start":1,"column_end":4}},{"value":"/ [^5]: Internet Engineering Task Force (February 2015),","span":{"file_name":"/Users/yoiwasaki/.cargo/registry/src/github.com-1ecc6299db9ec823/rand_hc-0.2.0/src/hc128.rs","byte_start":3686,"byte_end":3744,"line_start":64,"line_end":64,"column_start":1,"column_end":59}},{"value":"/       [\"Prohibiting RC4 Cipher Suites\"](https://tools.ietf.org/html/rfc7465).","span":{"file_name":"/Users/yoiwasaki/.cargo/registry/src/github.com-1ecc6299db9ec823/rand_hc-0.2.0/src/hc128.rs","byte_start":3745,"byte_end":3826,"line_start":65,"line_end":65,"column_start":1,"column_end":82}}]},{"kind":"Method","id":{"krate":0,"index":33},"span":{"file_name":"/Users/yoiwasaki/.cargo/registry/src/github.com-1ecc6299db9ec823/rand_hc-0.2.0/src/hc128.rs","byte_start":3943,"byte_end":3951,"line_start":71,"line_end":71,"column_start":8,"column_end":16},"name":"next_u32","qualname":"<Hc128Rng as rand_core::RngCore>::next_u32","value":"fn next_u32<'_>(&'_ mut Self) -> u32","parent":{"krate":4,"index":195},"children":[],"decl_id":{"krate":4,"index":196},"docs":"","sig":null,"attributes":[{"value":"inline","span":{"file_name":"/Users/yoiwasaki/.cargo/registry/src/github.com-1ecc6299db9ec823/rand_hc-0.2.0/src/hc128.rs","byte_start":3926,"byte_end":3935,"line_start":70,"line_end":70,"column_start":5,"column_end":14}}]},{"kind":"Method","id":{"krate":0,"index":34},"span":{"file_name":"/Users/yoiwasaki/.cargo/registry/src/github.com-1ecc6299db9ec823/rand_hc-0.2.0/src/hc128.rs","byte_start":4026,"byte_end":4034,"line_start":76,"line_end":76,"column_start":8,"column_end":16},"name":"next_u64","qualname":"<Hc128Rng as rand_core::RngCore>::next_u64","value":"fn next_u64<'_>(&'_ mut Self) -> u64","parent":{"krate":4,"index":195},"children":[],"decl_id":{"krate":4,"index":197},"docs":"","sig":null,"attributes":[{"value":"inline","span":{"file_name":"/Users/yoiwasaki/.cargo/registry/src/github.com-1ecc6299db9ec823/rand_hc-0.2.0/src/hc128.rs","byte_start":4009,"byte_end":4018,"line_start":75,"line_end":75,"column_start":5,"column_end":14}}]},{"kind":"Method","id":{"krate":0,"index":35},"span":{"file_name":"/Users/yoiwasaki/.cargo/registry/src/github.com-1ecc6299db9ec823/rand_hc-0.2.0/src/hc128.rs","byte_start":4109,"byte_end":4119,"line_start":81,"line_end":81,"column_start":8,"column_end":18},"name":"fill_bytes","qualname":"<Hc128Rng as rand_core::RngCore>::fill_bytes","value":"fn fill_bytes<'_, '_>(&'_ mut Self, &'_ mut [u8])","parent":{"krate":4,"index":195},"children":[],"decl_id":{"krate":4,"index":198},"docs":"","sig":null,"attributes":[{"value":"inline","span":{"file_name":"/Users/yoiwasaki/.cargo/registry/src/github.com-1ecc6299db9ec823/rand_hc-0.2.0/src/hc128.rs","byte_start":4092,"byte_end":4101,"line_start":80,"line_end":80,"column_start":5,"column_end":14}}]},{"kind":"Method","id":{"krate":0,"index":36},"span":{"file_name":"/Users/yoiwasaki/.cargo/registry/src/github.com-1ecc6299db9ec823/rand_hc-0.2.0/src/hc128.rs","byte_start":4210,"byte_end":4224,"line_start":86,"line_end":86,"column_start":8,"column_end":22},"name":"try_fill_bytes","qualname":"<Hc128Rng as rand_core::RngCore>::try_fill_bytes","value":"fn try_fill_bytes<'_, '_>(&'_ mut Self, &'_ mut [u8]) -> Result<(), Error>","parent":{"krate":4,"index":195},"children":[],"decl_id":{"krate":4,"index":199},"docs":"","sig":null,"attributes":[{"value":"inline","span":{"file_name":"/Users/yoiwasaki/.cargo/registry/src/github.com-1ecc6299db9ec823/rand_hc-0.2.0/src/hc128.rs","byte_start":4193,"byte_end":4202,"line_start":85,"line_end":85,"column_start":5,"column_end":14}}]},{"kind":"Method","id":{"krate":0,"index":39},"span":{"file_name":"/Users/yoiwasaki/.cargo/registry/src/github.com-1ecc6299db9ec823/rand_hc-0.2.0/src/hc128.rs","byte_start":4425,"byte_end":4434,"line_start":95,"line_end":95,"column_start":8,"column_end":17},"name":"from_seed","qualname":"<Hc128Rng as rand_core::SeedableRng>::from_seed","value":"fn from_seed(Self::Seed) -> Self","parent":{"krate":4,"index":201},"children":[],"decl_id":{"krate":4,"index":203},"docs":"","sig":null,"attributes":[{"value":"inline","span":{"file_name":"/Users/yoiwasaki/.cargo/registry/src/github.com-1ecc6299db9ec823/rand_hc-0.2.0/src/hc128.rs","byte_start":4408,"byte_end":4417,"line_start":94,"line_end":94,"column_start":5,"column_end":14}}]},{"kind":"Method","id":{"krate":0,"index":40},"span":{"file_name":"/Users/yoiwasaki/.cargo/registry/src/github.com-1ecc6299db9ec823/rand_hc-0.2.0/src/hc128.rs","byte_start":4548,"byte_end":4556,"line_start":100,"line_end":100,"column_start":8,"column_end":16},"name":"from_rng","qualname":"<Hc128Rng as rand_core::SeedableRng>::from_rng","value":"fn from_rng<R>(R) -> Result<Self, Error> where R: RngCore","parent":{"krate":4,"index":201},"children":[],"decl_id":{"krate":4,"index":207},"docs":"","sig":null,"attributes":[{"value":"inline","span":{"file_name":"/Users/yoiwasaki/.cargo/registry/src/github.com-1ecc6299db9ec823/rand_hc-0.2.0/src/hc128.rs","byte_start":4531,"byte_end":4540,"line_start":99,"line_end":99,"column_start":5,"column_end":14}}]},{"kind":"Struct","id":{"krate":0,"index":79},"span":{"file_name":"/Users/yoiwasaki/.cargo/registry/src/github.com-1ecc6299db9ec823/rand_hc-0.2.0/src/hc128.rs","byte_start":4780,"byte_end":4789,"line_start":109,"line_end":109,"column_start":12,"column_end":21},"name":"Hc128Core","qualname":"::hc128::Hc128Core","value":"Hc128Core {  }","parent":null,"children":[{"krate":0,"index":80},{"krate":0,"index":82}],"decl_id":null,"docs":" The core of `Hc128Rng`, used with `BlockRng`.\n","sig":null,"attributes":[{"value":"/ The core of `Hc128Rng`, used with `BlockRng`.","span":{"file_name":"/Users/yoiwasaki/.cargo/registry/src/github.com-1ecc6299db9ec823/rand_hc-0.2.0/src/hc128.rs","byte_start":4702,"byte_end":4751,"line_start":107,"line_end":107,"column_start":1,"column_end":50}}]},{"kind":"Method","id":{"krate":0,"index":44},"span":{"file_name":"/Users/yoiwasaki/.cargo/registry/src/github.com-1ecc6299db9ec823/rand_hc-0.2.0/src/hc128.rs","byte_start":4949,"byte_end":4952,"line_start":116,"line_end":116,"column_start":8,"column_end":11},"name":"fmt","qualname":"<Hc128Core as core::fmt::Debug>::fmt","value":"fn fmt<'_, '_, '_>(&'_ Self, &'_ mut fmt::Formatter) -> fmt::Result","parent":{"krate":1,"index":10264},"children":[],"decl_id":{"krate":1,"index":10265},"docs":"","sig":null,"attributes":[]},{"kind":"Method","id":{"krate":0,"index":49},"span":{"file_name":"/Users/yoiwasaki/.cargo/registry/src/github.com-1ecc6299db9ec823/rand_hc-0.2.0/src/hc128.rs","byte_start":5139,"byte_end":5147,"line_start":125,"line_end":125,"column_start":8,"column_end":16},"name":"generate","qualname":"<Hc128Core as rand_core::block::BlockRngCore>::generate","value":"fn generate<'_, '_>(&'_ mut Self, &'_ mut Self::Results)","parent":{"krate":4,"index":83},"children":[],"decl_id":{"krate":4,"index":86},"docs":"","sig":null,"attributes":[]},{"kind":"Method","id":{"krate":0,"index":62},"span":{"file_name":"/Users/yoiwasaki/.cargo/registry/src/github.com-1ecc6299db9ec823/rand_hc-0.2.0/src/hc128.rs","byte_start":14940,"byte_end":14949,"line_start":328,"line_end":328,"column_start":8,"column_end":17},"name":"from_seed","qualname":"<Hc128Core as rand_core::SeedableRng>::from_seed","value":"fn from_seed(Self::Seed) -> Self","parent":{"krate":4,"index":201},"children":[],"decl_id":{"krate":4,"index":203},"docs":" Create an HC-128 random number generator with a seed. The seed has to be\n 256 bits in length, matching the 128 bit `key` followed by 128 bit `iv`\n when HC-128 where to be used as a stream cipher.\n","sig":null,"attributes":[{"value":"/ Create an HC-128 random number generator with a seed. The seed has to be","span":{"file_name":"/Users/yoiwasaki/.cargo/registry/src/github.com-1ecc6299db9ec823/rand_hc-0.2.0/src/hc128.rs","byte_start":14719,"byte_end":14795,"line_start":325,"line_end":325,"column_start":5,"column_end":81}},{"value":"/ 256 bits in length, matching the 128 bit `key` followed by 128 bit `iv`","span":{"file_name":"/Users/yoiwasaki/.cargo/registry/src/github.com-1ecc6299db9ec823/rand_hc-0.2.0/src/hc128.rs","byte_start":14800,"byte_end":14875,"line_start":326,"line_end":326,"column_start":5,"column_end":80}},{"value":"/ when HC-128 where to be used as a stream cipher.","span":{"file_name":"/Users/yoiwasaki/.cargo/registry/src/github.com-1ecc6299db9ec823/rand_hc-0.2.0/src/hc128.rs","byte_start":14880,"byte_end":14932,"line_start":327,"line_end":327,"column_start":5,"column_end":57}}]}],"impls":[{"id":0,"kind":"Direct","span":{"file_name":"/Users/yoiwasaki/.cargo/registry/src/github.com-1ecc6299db9ec823/rand_hc-0.2.0/src/hc128.rs","byte_start":3911,"byte_end":3919,"line_start":69,"line_end":69,"column_start":18,"column_end":26},"value":"","parent":null,"children":[{"krate":0,"index":33},{"krate":0,"index":34},{"krate":0,"index":35},{"krate":0,"index":36}],"docs":"","sig":null,"attributes":[]},{"id":1,"kind":"Direct","span":{"file_name":"/Users/yoiwasaki/.cargo/registry/src/github.com-1ecc6299db9ec823/rand_hc-0.2.0/src/hc128.rs","byte_start":4342,"byte_end":4350,"line_start":91,"line_end":91,"column_start":22,"column_end":30},"value":"","parent":null,"children":[{"krate":0,"index":38},{"krate":0,"index":39},{"krate":0,"index":40}],"docs":"","sig":null,"attributes":[]},{"id":2,"kind":"Direct","span":{"file_name":"/Users/yoiwasaki/.cargo/registry/src/github.com-1ecc6299db9ec823/rand_hc-0.2.0/src/hc128.rs","byte_start":4689,"byte_end":4697,"line_start":105,"line_end":105,"column_start":20,"column_end":28},"value":"","parent":null,"children":[],"docs":"","sig":null,"attributes":[]},{"id":3,"kind":"Direct","span":{"file_name":"/Users/yoiwasaki/.cargo/registry/src/github.com-1ecc6299db9ec823/rand_hc-0.2.0/src/hc128.rs","byte_start":4930,"byte_end":4939,"line_start":115,"line_end":115,"column_start":21,"column_end":30},"value":"","parent":null,"children":[{"krate":0,"index":44}],"docs":"","sig":null,"attributes":[]},{"id":4,"kind":"Direct","span":{"file_name":"/Users/yoiwasaki/.cargo/registry/src/github.com-1ecc6299db9ec823/rand_hc-0.2.0/src/hc128.rs","byte_start":5068,"byte_end":5077,"line_start":121,"line_end":121,"column_start":23,"column_end":32},"value":"","parent":null,"children":[{"krate":0,"index":46},{"krate":0,"index":47},{"krate":0,"index":49}],"docs":"","sig":null,"attributes":[]},{"id":5,"kind":"Inherent","span":{"file_name":"/Users/yoiwasaki/.cargo/registry/src/github.com-1ecc6299db9ec823/rand_hc-0.2.0/src/hc128.rs","byte_start":7894,"byte_end":7903,"line_start":173,"line_end":173,"column_start":6,"column_end":15},"value":"","parent":null,"children":[{"krate":0,"index":51},{"krate":0,"index":52},{"krate":0,"index":53},{"krate":0,"index":54}],"docs":"","sig":null,"attributes":[]},{"id":6,"kind":"Direct","span":{"file_name":"/Users/yoiwasaki/.cargo/registry/src/github.com-1ecc6299db9ec823/rand_hc-0.2.0/src/hc128.rs","byte_start":14666,"byte_end":14675,"line_start":322,"line_end":322,"column_start":22,"column_end":31},"value":"","parent":null,"children":[{"krate":0,"index":60},{"krate":0,"index":62}],"docs":"","sig":null,"attributes":[]},{"id":7,"kind":"Direct","span":{"file_name":"/Users/yoiwasaki/.cargo/registry/src/github.com-1ecc6299db9ec823/rand_hc-0.2.0/src/hc128.rs","byte_start":15131,"byte_end":15140,"line_start":335,"line_end":335,"column_start":20,"column_end":29},"value":"","parent":null,"children":[],"docs":"","sig":null,"attributes":[]}],"refs":[],"macro_refs":[],"relations":[{"span":{"file_name":"/Users/yoiwasaki/.cargo/registry/src/github.com-1ecc6299db9ec823/rand_hc-0.2.0/src/hc128.rs","byte_start":3911,"byte_end":3919,"line_start":69,"line_end":69,"column_start":18,"column_end":26},"kind":{"Impl":{"id":0}},"from":{"krate":0,"index":72},"to":{"krate":4,"index":195}},{"span":{"file_name":"/Users/yoiwasaki/.cargo/registry/src/github.com-1ecc6299db9ec823/rand_hc-0.2.0/src/hc128.rs","byte_start":4342,"byte_end":4350,"line_start":91,"line_end":91,"column_start":22,"column_end":30},"kind":{"Impl":{"id":1}},"from":{"krate":0,"index":72},"to":{"krate":4,"index":201}},{"span":{"file_name":"/Users/yoiwasaki/.cargo/registry/src/github.com-1ecc6299db9ec823/rand_hc-0.2.0/src/hc128.rs","byte_start":4689,"byte_end":4697,"line_start":105,"line_end":105,"column_start":20,"column_end":28},"kind":{"Impl":{"id":2}},"from":{"krate":0,"index":72},"to":{"krate":4,"index":200}},{"span":{"file_name":"/Users/yoiwasaki/.cargo/registry/src/github.com-1ecc6299db9ec823/rand_hc-0.2.0/src/hc128.rs","byte_start":4930,"byte_end":4939,"line_start":115,"line_end":115,"column_start":21,"column_end":30},"kind":{"Impl":{"id":3}},"from":{"krate":0,"index":79},"to":{"krate":1,"index":10264}},{"span":{"file_name":"/Users/yoiwasaki/.cargo/registry/src/github.com-1ecc6299db9ec823/rand_hc-0.2.0/src/hc128.rs","byte_start":5068,"byte_end":5077,"line_start":121,"line_end":121,"column_start":23,"column_end":32},"kind":{"Impl":{"id":4}},"from":{"krate":0,"index":79},"to":{"krate":4,"index":83}},{"span":{"file_name":"/Users/yoiwasaki/.cargo/registry/src/github.com-1ecc6299db9ec823/rand_hc-0.2.0/src/hc128.rs","byte_start":7894,"byte_end":7903,"line_start":173,"line_end":173,"column_start":6,"column_end":15},"kind":{"Impl":{"id":5}},"from":{"krate":0,"index":79},"to":{"krate":4294967295,"index":4294967295}},{"span":{"file_name":"/Users/yoiwasaki/.cargo/registry/src/github.com-1ecc6299db9ec823/rand_hc-0.2.0/src/hc128.rs","byte_start":14666,"byte_end":14675,"line_start":322,"line_end":322,"column_start":22,"column_end":31},"kind":{"Impl":{"id":6}},"from":{"krate":0,"index":79},"to":{"krate":4,"index":201}},{"span":{"file_name":"/Users/yoiwasaki/.cargo/registry/src/github.com-1ecc6299db9ec823/rand_hc-0.2.0/src/hc128.rs","byte_start":15131,"byte_end":15140,"line_start":335,"line_end":335,"column_start":20,"column_end":29},"kind":{"Impl":{"id":7}},"from":{"krate":0,"index":79},"to":{"krate":4,"index":200}}]}